{"id":"24","titulo":"Volume \u00fatil (% MLT*)","titulo_eng":"Usable volume (% of long-term average)","tipo":"barra","paleta":"neutro","girar":"n","percent_axis":"n","casas_decimais":"2","prefix":"","sufix":"","min":"","max":"","label_pos":"inside","legendas":"Legenda|01\/12\/2013*Dec. 1, 2013|01\/12\/2014*Dec. 1, 2014","valores":"Camargos|33,76|11,51|Emborca\u00e7\u00e3o|32,74|15,92|Irap\u00e9|40,21|32,44|Nova Ponte|33,17|11,28|Queimado|46,55|6,32|Tr\u00eas Marias|21,44|4,81","altera_tipo":"","vertical_offset":"0","horizontal_offset":"","mostrar_legenda":"s","legenda_h":"center","legenda_v":"bottom","script":"","datasource":"[{\"legenda\": \"Camargos\", \"01\/12\/2013*dec.1,2013\": \"33,76\", \"01\/12\/2014*dec.1,2014\": \"11,51\"}, {\"legenda\": \"Emborca\u00e7\u00e3o\", \"01\/12\/2013*dec.1,2013\": \"32,74\", \"01\/12\/2014*dec.1,2014\": \"15,92\"}, {\"legenda\": \"Irap\u00e9\", \"01\/12\/2013*dec.1,2013\": \"40,21\", \"01\/12\/2014*dec.1,2014\": \"32,44\"}, {\"legenda\": \"Nova Ponte\", \"01\/12\/2013*dec.1,2013\": \"33,17\", \"01\/12\/2014*dec.1,2014\": \"11,28\"}, {\"legenda\": \"Queimado\", \"01\/12\/2013*dec.1,2013\": \"46,55\", \"01\/12\/2014*dec.1,2014\": \"6,32\"}, {\"legenda\": \"Tr\u00eas Marias\", \"01\/12\/2013*dec.1,2013\": \"21,44\", \"01\/12\/2014*dec.1,2014\": \"4,81\"}]","ordem":"999","data_cadastro":"2015-03-27 15:02:51"}